{
  "cart": [
    4,
    6,
    8
  ],
  "my_cards": [
    {
      "0": 2,
      "id": "bdcb"
    },
    {
      "0": 2,
      "id": "ac20"
    },
    {
      "0": 2,
      "id": "dff7"
    },
    {
      "0": 2,
      "id": "b538"
    },
    {
      "0": 2,
      "id": "b3cf"
    },
    {
      "0": 2,
      "id": "5416"
    },
    {
      "0": 2,
      "id": "c133"
    },
    {
      "0": 2,
      "id": "b6eb"
    },
    {
      "0": 2,
      "id": "a3eb"
    },
    {
      "0": 2,
      "id": "e62a"
    },
    {
      "0": 2,
      "id": "8b4e"
    },
    {
      "0": 7,
      "id": "1edd"
    },
    {
      "0": 7,
      "id": "1c96"
    },
    {
      "0": 2,
      "id": "da1f"
    }
  ]
}